pynoptes/__init__.py
pynoptes/dataloaders/__init__.py
pynoptes/dataloaders/vision.py
pynoptes/detection/__init__.py
pynoptes/detection/boxes.py
pynoptes/postprocessing/__init__.py
pynoptes/preprocessing/__init__.py
pynoptes/pretrained/__init__.py
pynoptes/reidentification/__init__.py
pynoptes/segmentation/__init__.py
tests/__init__.py
tests/test_detection.py
pynoptes-0.0.7a0.dist-info/LICENSE
pynoptes-0.0.7a0.dist-info/METADATA
pynoptes-0.0.7a0.dist-info/WHEEL
pynoptes-0.0.7a0.dist-info/top_level.txt
pynoptes-0.0.7a0.dist-info/RECORD
