Metadata-Version: 2.1
Name: pynoptes
Version: 0.0.7a0
Summary: Python Package for Object Detection and Tracking
Home-page: https://github.com/fubel/pynoptes
Author: Fabian Herzog
Author-email: mail@fabianherzog.me
License: UNKNOWN
Platform: UNKNOWN
Classifier: Programming Language :: Python :: 3
Classifier: License :: OSI Approved :: MIT License
Classifier: Operating System :: OS Independent
